overleaf2arxiv/main.py
overleaf2arxiv-0.2.2.dist-info/licenses/LICENSE
overleaf2arxiv-0.2.2.dist-info/METADATA
overleaf2arxiv-0.2.2.dist-info/WHEEL
overleaf2arxiv-0.2.2.dist-info/entry_points.txt
overleaf2arxiv-0.2.2.dist-info/top_level.txt
overleaf2arxiv-0.2.2.dist-info/RECORD
