Metadata-Version: 2.4
Name: overleaf2arxiv
Version: 0.2.2
Summary: A tool to convert Overleaf projects to arXiv-compatible formats
Home-page: https://github.com/abhayd/Overleaf2Arxiv
Author: Abhay Deshpande
Classifier: Development Status :: 3 - Alpha
Classifier: Intended Audience :: Science/Research
Classifier: License :: OSI Approved :: MIT License
Classifier: Programming Language :: Python :: 3
Classifier: Operating System :: MacOS
Classifier: Operating System :: POSIX
Requires-Python: >=3.8
License-File: LICENSE
Requires-Dist: pyoverleaf
Dynamic: author
Dynamic: classifier
Dynamic: description
Dynamic: description-content-type
Dynamic: home-page
Dynamic: license-file
Dynamic: requires-dist
Dynamic: requires-python
Dynamic: summary
